todotree/Commands/AbstractCommand.py
todotree/Commands/Add.py
todotree/Commands/AddX.py
todotree/Commands/Addons.py
todotree/Commands/Append.py
todotree/Commands/Cd.py
todotree/Commands/Compress.py
todotree/Commands/Context.py
todotree/Commands/Do.py
todotree/Commands/Due.py
todotree/Commands/Edit.py
todotree/Commands/Filter.py
todotree/Commands/Git.py
todotree/Commands/Init.py
todotree/Commands/List.py
todotree/Commands/ListDone.py
todotree/Commands/PrintRaw.py
todotree/Commands/Priority.py
todotree/Commands/Project.py
todotree/Commands/Recur.py
todotree/Commands/Revive.py
todotree/Commands/Schedule.py
todotree/Commands/Stale_add.py
todotree/Commands/Stale_list.py
todotree/Commands/Stale_revive.py
todotree/Commands/Version.py
todotree/Config/AbstractSubConfig.py
todotree/Config/Config.py
todotree/Config/ConsolePrefixes.py
todotree/Config/ConsolePrefixesInit.py
todotree/Config/GitHandler.py
todotree/Config/Paths.py
todotree/Config/TreePrint.py
todotree/Errors/ConfigFileNotFoundError.py
todotree/Errors/DoneFileNotFoundError.py
todotree/Errors/GitError.py
todotree/Errors/InvalidPriorityError.py
todotree/Errors/NoSuchTaskError.py
todotree/Errors/ProjectFolderError.py
todotree/Errors/RecurDateStampError.py
todotree/Errors/RecurParseError.py
todotree/Errors/StaleFileNotFoundError.py
todotree/Errors/TaskParseError.py
todotree/Errors/TodoFileNotFoundError.py
todotree/Errors/TodotreeError.py
todotree/Main.py
todotree/MainUtils.py
todotree/Managers/AbstractManager.py
todotree/Managers/DoneManager.py
todotree/Managers/RecurManager.py
todotree/Managers/StaleManager.py
todotree/Managers/TaskManager.py
todotree/Task/ConsoleTask.py
todotree/Task/DoneTask.py
todotree/Task/RecurTask.py
todotree/Task/Task.py
todotree/Tree.py
todotree/__init__.py
todotree/examples/config.yaml
todotree/examples/done.txt
todotree/examples/recur.txt
todotree/examples/stale.txt
todotree/examples/todo.txt
todotree-4.3.1.dist-info/METADATA
todotree-4.3.1.dist-info/WHEEL
todotree-4.3.1.dist-info/entry_points.txt
todotree-4.3.1.dist-info/licenses/LICENSE
todotree-4.3.1.dist-info/RECORD
