Metadata-Version: 2.4
Name: todotree
Version: 4.3.1
Summary: todo.txt manager which adds tree printing
License: Unlicense
License-File: LICENSE
Author: chim1aap
Author-email: fkjansen@protonmail.com
Requires-Python: >=3.10,<4.0
Classifier: License :: OSI Approved
Classifier: Programming Language :: Python :: 3
Classifier: Programming Language :: Python :: 3.10
Classifier: Programming Language :: Python :: 3.11
Classifier: Programming Language :: Python :: 3.12
Classifier: Programming Language :: Python :: 3.13
Classifier: Programming Language :: Python :: 3.14
Provides-Extra: init
Requires-Dist: click (>=8.1.3,<9.0.0)
Requires-Dist: dateutils (>=0.6.12,<0.7.0)
Requires-Dist: gitpython (>=3.1.31,<4.0.0)
Requires-Dist: pyyaml (>=6.0.1,<7.0.0)
Requires-Dist: ruamel-yaml (>=0.18,<0.19) ; extra == "init"
Requires-Dist: xdg-base-dirs (>=6.0.0,<7.0.0)
Project-URL: Documentation, https://chim1aap.gitlab.io/todotree/
Project-URL: Repository, https://gitlab.com/chim1aap/todotree
